<annotation>
	<folder></folder>
	<filename>151_spot_jpg.rf.89dddd102d63bf1d93ba2170e97b75fb.jpg</filename>
	<path>151_spot_jpg.rf.89dddd102d63bf1d93ba2170e97b75fb.jpg</path>
	<source>
		<database>roboflow.ai</database>
	</source>
	<size>
		<width>416</width>
		<height>416</height>
		<depth>3</depth>
	</size>
	<segmented>0</segmented>
	<object>
		<name>Spot</name>
		<pose>Unspecified</pose>
		<truncated>0</truncated>
		<difficult>0</difficult>
		<occluded>0</occluded>
		<bndbox>
			<xmin>141</xmin>
			<xmax>241</xmax>
			<ymin>67</ymin>
			<ymax>317</ymax>
		</bndbox>
	</object>
	<object>
		<name>Spot</name>
		<pose>Unspecified</pose>
		<truncated>0</truncated>
		<difficult>0</difficult>
		<occluded>0</occluded>
		<bndbox>
			<xmin>249</xmin>
			<xmax>286</xmax>
			<ymin>223</ymin>
			<ymax>319</ymax>
		</bndbox>
	</object>
	<object>
		<name>Spot</name>
		<pose>Unspecified</pose>
		<truncated>0</truncated>
		<difficult>0</difficult>
		<occluded>0</occluded>
		<bndbox>
			<xmin>236</xmin>
			<xmax>294</xmax>
			<ymin>4</ymin>
			<ymax>58</ymax>
		</bndbox>
	</object>
	<object>
		<name>Spot</name>
		<pose>Unspecified</pose>
		<truncated>0</truncated>
		<difficult>0</difficult>
		<occluded>0</occluded>
		<bndbox>
			<xmin>21</xmin>
			<xmax>95</xmax>
			<ymin>6</ymin>
			<ymax>96</ymax>
		</bndbox>
	</object>
</annotation>
